{"directed": false, "multigraph": false, "graph": {}, "nodes": [{"score": 0.51, "group": 1, "id": "akilov"}, {"score": 0.223, "group": 2, "id": "border"}, {"score": 0.128, "group": 0, "id": "trump"}, {"score": 0.157, "group": 2, "id": "asylum"}, {"score": 0.262, "group": 1, "id": "sweden"}, {"score": 0.249, "group": 1, "id": "stockholm"}, {"score": 0.247, "group": 1, "id": "truck"}, {"score": 0.149, "group": 2, "id": "seekers"}, {"score": 0.091, "group": 0, "id": "children"}, {"score": 0.091, "group": 0, "id": "court"}, {"score": 0.205, "group": 1, "id": "attack"}, {"score": 0.152, "group": 1, "id": "sentence"}, {"score": 0.145, "group": 1, "id": "murder"}, {"score": 0.084, "group": 1, "id": "attempted"}, {"score": 0.216, "group": 2, "id": "tijuana"}, {"score": 0.179, "group": 2, "id": "crossing"}, {"score": 0.148, "group": 2, "id": "wait"}, {"score": 0.281, "group": 4, "id": "jordan"}, {"score": 0.194, "group": 4, "id": "protests"}, {"score": 0.193, "group": 4, "id": "tax"}, {"score": 0.155, "group": 4, "id": "razzaz"}, {"score": 0.148, "group": 4, "id": "imf"}, {"score": 0.144, "group": 4, "id": "bill"}, {"score": 0.248, "group": 6, "id": "facebook"}, {"score": 0.211, "group": 6, "id": "sri"}, {"score": 0.194, "group": 6, "id": "lanka"}, {"score": 0.167, "group": 6, "id": "sinhala"}, {"score": 0.277, "group": 9, "id": "myanmar"}, {"score": 0.198, "group": 9, "id": "rohingya"}, {"score": 0.158, "group": 6, "id": "girl"}, {"score": 0.147, "group": 6, "id": "wiesbaden"}, {"score": 0.135, "group": 6, "id": "iraqi"}, {"score": 0.129, "group": 6, "id": "germany"}, {"score": 0.131, "group": 9, "id": "bangladesh"}, {"score": 0.429, "group": 8, "id": "greece"}, {"score": 0.384, "group": 8, "id": "turkey"}, {"score": 0.241, "group": 8, "id": "greek"}, {"score": 0.231, "group": 8, "id": "readmission"}, {"score": 0.211, "group": 8, "id": "cavusoglu"}, {"score": 0.164, "group": 8, "id": "coup"}, {"score": 0.146, "group": 8, "id": "bilateral"}, {"score": 0.131, "group": 8, "id": "soldiers"}, {"score": 0.121, "group": 8, "id": "suspended"}, {"score": 0.133, "group": 9, "id": "agreement"}, {"score": 0.132, "group": 9, "id": "rakhine"}, {"score": 0.124, "group": 9, "id": "repatriation"}, {"score": 0.119, "group": 9, "id": "release"}], "links": [{"source": "akilov", "target": "seekers"}, {"source": "akilov", "target": "stockholm"}, {"source": "akilov", "target": "trump"}, {"source": "akilov", "target": "truck"}, {"source": "akilov", "target": "court"}, {"source": "akilov", "target": "border"}, {"source": "akilov", "target": "asylum"}, {"source": "akilov", "target": "children"}, {"source": "akilov", "target": "sweden"}, {"source": "akilov", "target": "attack"}, {"source": "akilov", "target": "sentence"}, {"source": "akilov", "target": "attempted"}, {"source": "akilov", "target": "murder"}, {"source": "border", "target": "seekers"}, {"source": "border", "target": "stockholm"}, {"source": "border", "target": "trump"}, {"source": "border", "target": "truck"}, {"source": "border", "target": "court"}, {"source": "border", "target": "asylum"}, {"source": "border", "target": "children"}, {"source": "border", "target": "sweden"}, {"source": "border", "target": "tijuana"}, {"source": "border", "target": "wait"}, {"source": "border", "target": "crossing"}, {"source": "trump", "target": "seekers"}, {"source": "trump", "target": "stockholm"}, {"source": "trump", "target": "truck"}, {"source": "trump", "target": "court"}, {"source": "trump", "target": "asylum"}, {"source": "trump", "target": "children"}, {"source": "trump", "target": "sweden"}, {"source": "asylum", "target": "seekers"}, {"source": "asylum", "target": "stockholm"}, {"source": "asylum", "target": "truck"}, {"source": "asylum", "target": "court"}, {"source": "asylum", "target": "children"}, {"source": "asylum", "target": "sweden"}, {"source": "asylum", "target": "tijuana"}, {"source": "asylum", "target": "wait"}, {"source": "asylum", "target": "crossing"}, {"source": "sweden", "target": "seekers"}, {"source": "sweden", "target": "stockholm"}, {"source": "sweden", "target": "truck"}, {"source": "sweden", "target": "court"}, {"source": "sweden", "target": "children"}, {"source": "sweden", "target": "attack"}, {"source": "sweden", "target": "sentence"}, {"source": "sweden", "target": "attempted"}, {"source": "sweden", "target": "murder"}, {"source": "stockholm", "target": "seekers"}, {"source": "stockholm", "target": "truck"}, {"source": "stockholm", "target": "court"}, {"source": "stockholm", "target": "children"}, {"source": "stockholm", "target": "attack"}, {"source": "stockholm", "target": "sentence"}, {"source": "stockholm", "target": "attempted"}, {"source": "stockholm", "target": "murder"}, {"source": "truck", "target": "seekers"}, {"source": "truck", "target": "court"}, {"source": "truck", "target": "children"}, {"source": "truck", "target": "attack"}, {"source": "truck", "target": "sentence"}, {"source": "truck", "target": "attempted"}, {"source": "truck", "target": "murder"}, {"source": "seekers", "target": "court"}, {"source": "seekers", "target": "children"}, {"source": "seekers", "target": "tijuana"}, {"source": "seekers", "target": "wait"}, {"source": "seekers", "target": "crossing"}, {"source": "children", "target": "court"}, {"source": "attack", "target": "sentence"}, {"source": "attack", "target": "attempted"}, {"source": "attack", "target": "murder"}, {"source": "sentence", "target": "attempted"}, {"source": "sentence", "target": "murder"}, {"source": "murder", "target": "attempted"}, {"source": "tijuana", "target": "wait"}, {"source": "tijuana", "target": "crossing"}, {"source": "crossing", "target": "wait"}, {"source": "jordan", "target": "imf"}, {"source": "jordan", "target": "protests"}, {"source": "jordan", "target": "bill"}, {"source": "jordan", "target": "razzaz"}, {"source": "jordan", "target": "tax"}, {"source": "protests", "target": "imf"}, {"source": "protests", "target": "bill"}, {"source": "protests", "target": "razzaz"}, {"source": "protests", "target": "tax"}, {"source": "tax", "target": "imf"}, {"source": "tax", "target": "bill"}, {"source": "tax", "target": "razzaz"}, {"source": "razzaz", "target": "imf"}, {"source": "razzaz", "target": "bill"}, {"source": "imf", "target": "bill"}, {"source": "facebook", "target": "sri"}, {"source": "facebook", "target": "lanka"}, {"source": "facebook", "target": "sinhala"}, {"source": "facebook", "target": "rohingya"}, {"source": "facebook", "target": "myanmar"}, {"source": "facebook", "target": "iraqi"}, {"source": "facebook", "target": "germany"}, {"source": "facebook", "target": "wiesbaden"}, {"source": "facebook", "target": "girl"}, {"source": "sri", "target": "lanka"}, {"source": "sri", "target": "sinhala"}, {"source": "sri", "target": "rohingya"}, {"source": "sri", "target": "myanmar"}, {"source": "sri", "target": "iraqi"}, {"source": "sri", "target": "germany"}, {"source": "sri", "target": "wiesbaden"}, {"source": "sri", "target": "girl"}, {"source": "lanka", "target": "sinhala"}, {"source": "lanka", "target": "rohingya"}, {"source": "lanka", "target": "myanmar"}, {"source": "lanka", "target": "iraqi"}, {"source": "lanka", "target": "germany"}, {"source": "lanka", "target": "wiesbaden"}, {"source": "lanka", "target": "girl"}, {"source": "sinhala", "target": "rohingya"}, {"source": "sinhala", "target": "myanmar"}, {"source": "sinhala", "target": "iraqi"}, {"source": "sinhala", "target": "germany"}, {"source": "sinhala", "target": "wiesbaden"}, {"source": "sinhala", "target": "girl"}, {"source": "myanmar", "target": "rohingya"}, {"source": "myanmar", "target": "bangladesh"}, {"source": "myanmar", "target": "release"}, {"source": "myanmar", "target": "rakhine"}, {"source": "myanmar", "target": "repatriation"}, {"source": "myanmar", "target": "agreement"}, {"source": "rohingya", "target": "bangladesh"}, {"source": "rohingya", "target": "release"}, {"source": "rohingya", "target": "rakhine"}, {"source": "rohingya", "target": "repatriation"}, {"source": "rohingya", "target": "agreement"}, {"source": "girl", "target": "iraqi"}, {"source": "girl", "target": "germany"}, {"source": "girl", "target": "wiesbaden"}, {"source": "wiesbaden", "target": "iraqi"}, {"source": "wiesbaden", "target": "germany"}, {"source": "iraqi", "target": "germany"}, {"source": "bangladesh", "target": "release"}, {"source": "bangladesh", "target": "rakhine"}, {"source": "bangladesh", "target": "repatriation"}, {"source": "bangladesh", "target": "agreement"}, {"source": "greece", "target": "readmission"}, {"source": "greece", "target": "coup"}, {"source": "greece", "target": "bilateral"}, {"source": "greece", "target": "suspended"}, {"source": "greece", "target": "greek"}, {"source": "greece", "target": "turkey"}, {"source": "greece", "target": "cavusoglu"}, {"source": "greece", "target": "soldiers"}, {"source": "turkey", "target": "readmission"}, {"source": "turkey", "target": "coup"}, {"source": "turkey", "target": "bilateral"}, {"source": "turkey", "target": "suspended"}, {"source": "turkey", "target": "greek"}, {"source": "turkey", "target": "cavusoglu"}, {"source": "turkey", "target": "soldiers"}, {"source": "greek", "target": "readmission"}, {"source": "greek", "target": "coup"}, {"source": "greek", "target": "bilateral"}, {"source": "greek", "target": "suspended"}, {"source": "greek", "target": "cavusoglu"}, {"source": "greek", "target": "soldiers"}, {"source": "readmission", "target": "coup"}, {"source": "readmission", "target": "bilateral"}, {"source": "readmission", "target": "suspended"}, {"source": "readmission", "target": "cavusoglu"}, {"source": "readmission", "target": "soldiers"}, {"source": "cavusoglu", "target": "coup"}, {"source": "cavusoglu", "target": "bilateral"}, {"source": "cavusoglu", "target": "suspended"}, {"source": "cavusoglu", "target": "soldiers"}, {"source": "coup", "target": "bilateral"}, {"source": "coup", "target": "suspended"}, {"source": "coup", "target": "soldiers"}, {"source": "bilateral", "target": "suspended"}, {"source": "bilateral", "target": "soldiers"}, {"source": "soldiers", "target": "suspended"}, {"source": "agreement", "target": "release"}, {"source": "agreement", "target": "rakhine"}, {"source": "agreement", "target": "repatriation"}, {"source": "rakhine", "target": "release"}, {"source": "rakhine", "target": "repatriation"}, {"source": "repatriation", "target": "release"}]}